django_logbox/__init__.py
django_logbox/admin.py
django_logbox/app_settings.py
django_logbox/apps.py
django_logbox/filtering.py
django_logbox/locale/ko_KR/LC_MESSAGES/django.mo
django_logbox/locale/ko_KR/LC_MESSAGES/django.po
django_logbox/logging.py
django_logbox/middlewares.py
django_logbox/migrations/0001_initial.py
django_logbox/migrations/0002_remove_serverlog_duration.py
django_logbox/migrations/0003_rename_exception_serverlog_exception_type_and_more.py
django_logbox/migrations/0004_alter_serverlog_client_ip_and_more.py
django_logbox/migrations/0005_alter_serverlog_options_serverlog_browser_and_more.py
django_logbox/migrations/0006_backfill_device_os_browser_fields.py
django_logbox/migrations/0007_serverlog_user_alter_serverlog_querystring.py
django_logbox/migrations/0008_serverlog_server_host_serverlog_server_port.py
django_logbox/migrations/0009_backfill_server_side_info_fields.py
django_logbox/migrations/__init__.py
django_logbox/models.py
django_logbox/static/django_logbox/css/style.css
django_logbox/static/django_logbox/js/chart.umd.min.js
django_logbox/static/django_logbox/js/chartjs-plugin-datalabels.min.js
django_logbox/templates/change_list.html
django_logbox/threading.py
django_logbox/utils.py
django_logbox-1.1.1.dist-info/METADATA
django_logbox-1.1.1.dist-info/WHEEL
django_logbox-1.1.1.dist-info/RECORD
