Metadata-Version: 2.4
Name: django-logbox
Version: 1.1.1
Summary: Your small, but useful django log box. 📦
Author: tgoddessana
Author-email: twicegoddessana1229@gmail.com
Requires-Python: >=3.9,<4.0
Classifier: Programming Language :: Python :: 3
Classifier: Programming Language :: Python :: 3.9
Classifier: Programming Language :: Python :: 3.10
Classifier: Programming Language :: Python :: 3.11
Classifier: Programming Language :: Python :: 3.12
Classifier: Programming Language :: Python :: 3.13
Classifier: Programming Language :: Python :: 3.14
Requires-Dist: django (>=4.2)
Requires-Dist: ua-parser[regex] (>=1.0.1,<2.0.0)
